{
	"file_path": "C:\\Users\\gabri\\AppData\\Local\\Packages\\Microsoft.MinecraftUWP_8wekyb3d8bbwe\\LocalState\\games\\com.mojang\\development_behavior_packs\\[Furniture] Ghoulcraft BE BP\\blocks\\pillsingle_lime.json",
	"file_type": "block",
	"format_version": 1,
	"file_uuid": "5eebfc3e_3fc8_4916_afa1_46fe3f1c7744",
	"file_version": 14,
	"cache_content": {
		"children": [
			{
				"open": {
					"minecraft:block": {
						"description": {
							"properties": {
								"bridge:block_rotation": [
									2,
									3,
									4,
									5
								]
							},
							"identifier": "ghoulcraft:pillsingle_lime"
						},
						"permutations": [
							{
								"condition": "query.block_property('bridge:block_rotation') == 2",
								"components": {
									"minecraft:rotation": [
										0,
										180,
										0
									]
								}
							},
							{
								"condition": "query.block_property('bridge:block_rotation') == 3",
								"components": {
									"minecraft:rotation": [
										0,
										0,
										0
									]
								}
							},
							{
								"condition": "query.block_property('bridge:block_rotation') == 4",
								"components": {
									"minecraft:rotation": [
										0,
										270,
										0
									]
								}
							},
							{
								"condition": "query.block_property('bridge:block_rotation') == 5",
								"components": {
									"minecraft:rotation": [
										0,
										90,
										0
									]
								}
							}
						],
						"components": {
							"minecraft:on_player_placing": {
								"event": "bridge:update_rotation"
							},
							"minecraft:geometry": "geometry.pillsingle_lime",
							"minecraft:material_instances": {
								"*": {
									"texture": "noxlime",
									"render_method": "blend"
								}
							},
							"minecraft:pick_collision": {
								"origin": [
									-7,
									0,
									-7
								],
								"size": [
									14,
									4,
									14
								]
							},
							"minecraft:entity_collision": {
								"origin": [
									-7,
									0,
									-7
								],
								"size": [
									14,
									4,
									14
								]
							},
							"minecraft:block_light_emission": 0,
							"minecraft:block_light_absorption": 0
						},
						"events": {
							"bridge:update_rotation": {
								"set_block_property": {
									"bridge:block_rotation": "query.cardinal_facing_2d"
								}
							}
						}
					},
					"format_version": "1.16.100"
				},
				"key": "minecraft:block",
				"children": [
					{
						"open": {
							"description": {
								"properties": {
									"bridge:block_rotation": [
										2,
										3,
										4,
										5
									]
								},
								"identifier": "ghoulcraft:pillsingle_lime"
							},
							"permutations": [
								{
									"condition": "query.block_property('bridge:block_rotation') == 2",
									"components": {
										"minecraft:rotation": [
											0,
											180,
											0
										]
									}
								},
								{
									"condition": "query.block_property('bridge:block_rotation') == 3",
									"components": {
										"minecraft:rotation": [
											0,
											0,
											0
										]
									}
								},
								{
									"condition": "query.block_property('bridge:block_rotation') == 4",
									"components": {
										"minecraft:rotation": [
											0,
											270,
											0
										]
									}
								},
								{
									"condition": "query.block_property('bridge:block_rotation') == 5",
									"components": {
										"minecraft:rotation": [
											0,
											90,
											0
										]
									}
								}
							],
							"components": {
								"minecraft:on_player_placing": {
									"event": "bridge:update_rotation"
								},
								"minecraft:geometry": "geometry.pillsingle_lime",
								"minecraft:material_instances": {
									"*": {
										"texture": "noxlime",
										"render_method": "blend"
									}
								},
								"minecraft:pick_collision": {
									"origin": [
										-7,
										0,
										-7
									],
									"size": [
										14,
										4,
										14
									]
								},
								"minecraft:entity_collision": {
									"origin": [
										-7,
										0,
										-7
									],
									"size": [
										14,
										4,
										14
									]
								},
								"minecraft:block_light_emission": 0,
								"minecraft:block_light_absorption": 0
							},
							"events": {
								"bridge:update_rotation": {
									"set_block_property": {
										"bridge:block_rotation": "query.cardinal_facing_2d"
									}
								}
							}
						},
						"key": "description",
						"is_minified": true,
						"children": {
							"properties": {
								"bridge:block_rotation": [
									2,
									3,
									4,
									5
								]
							},
							"identifier": "ghoulcraft:pillsingle_lime"
						}
					},
					{
						"key": "permutations",
						"is_minified": true,
						"children": [
							{
								"condition": "query.block_property('bridge:block_rotation') == 2",
								"components": {
									"minecraft:rotation": [
										0,
										180,
										0
									]
								}
							},
							{
								"condition": "query.block_property('bridge:block_rotation') == 3",
								"components": {
									"minecraft:rotation": [
										0,
										0,
										0
									]
								}
							},
							{
								"condition": "query.block_property('bridge:block_rotation') == 4",
								"components": {
									"minecraft:rotation": [
										0,
										270,
										0
									]
								}
							},
							{
								"condition": "query.block_property('bridge:block_rotation') == 5",
								"components": {
									"minecraft:rotation": [
										0,
										90,
										0
									]
								}
							}
						]
					},
					{
						"open": {
							"description": {
								"properties": {
									"bridge:block_rotation": [
										2,
										3,
										4,
										5
									]
								},
								"identifier": "ghoulcraft:pillsingle_lime"
							},
							"permutations": [
								{
									"condition": "query.block_property('bridge:block_rotation') == 2",
									"components": {
										"minecraft:rotation": [
											0,
											180,
											0
										]
									}
								},
								{
									"condition": "query.block_property('bridge:block_rotation') == 3",
									"components": {
										"minecraft:rotation": [
											0,
											0,
											0
										]
									}
								},
								{
									"condition": "query.block_property('bridge:block_rotation') == 4",
									"components": {
										"minecraft:rotation": [
											0,
											270,
											0
										]
									}
								},
								{
									"condition": "query.block_property('bridge:block_rotation') == 5",
									"components": {
										"minecraft:rotation": [
											0,
											90,
											0
										]
									}
								}
							],
							"components": {
								"minecraft:on_player_placing": {
									"event": "bridge:update_rotation"
								},
								"minecraft:geometry": "geometry.pillsingle_lime",
								"minecraft:material_instances": {
									"*": {
										"texture": "noxlime",
										"render_method": "blend"
									}
								},
								"minecraft:pick_collision": {
									"origin": [
										-7,
										0,
										-7
									],
									"size": [
										14,
										4,
										14
									]
								},
								"minecraft:entity_collision": {
									"origin": [
										-7,
										0,
										-7
									],
									"size": [
										14,
										4,
										14
									]
								},
								"minecraft:block_light_emission": 0,
								"minecraft:block_light_absorption": 0
							},
							"events": {
								"bridge:update_rotation": {
									"set_block_property": {
										"bridge:block_rotation": "query.cardinal_facing_2d"
									}
								}
							}
						},
						"key": "components",
						"children": [
							{
								"key": "minecraft:on_player_placing",
								"is_minified": true,
								"children": {
									"event": "bridge:update_rotation"
								}
							},
							{
								"open": {
									"minecraft:on_player_placing": {
										"event": "bridge:update_rotation"
									},
									"minecraft:geometry": "geometry.pillsingle_lime",
									"minecraft:material_instances": {
										"*": {
											"texture": "noxlime",
											"render_method": "blend"
										}
									},
									"minecraft:pick_collision": {
										"origin": [
											-7,
											0,
											-7
										],
										"size": [
											14,
											4,
											14
										]
									},
									"minecraft:entity_collision": {
										"origin": [
											-7,
											0,
											-7
										],
										"size": [
											14,
											4,
											14
										]
									},
									"minecraft:block_light_emission": 0,
									"minecraft:block_light_absorption": 0
								},
								"data": "geometry.pillsingle_lime",
								"key": "minecraft:geometry"
							},
							{
								"open": {
									"minecraft:on_player_placing": {
										"event": "bridge:update_rotation"
									},
									"minecraft:geometry": "geometry.pillsingle_lime",
									"minecraft:material_instances": {
										"*": {
											"texture": "noxlime",
											"render_method": "blend"
										}
									},
									"minecraft:pick_collision": {
										"origin": [
											-7,
											0,
											-7
										],
										"size": [
											14,
											4,
											14
										]
									},
									"minecraft:entity_collision": {
										"origin": [
											-7,
											0,
											-7
										],
										"size": [
											14,
											4,
											14
										]
									},
									"minecraft:block_light_emission": 0,
									"minecraft:block_light_absorption": 0
								},
								"key": "minecraft:material_instances",
								"children": [
									{
										"open": {
											"*": {
												"texture": "noxlime",
												"render_method": "blend"
											}
										},
										"key": "*",
										"is_minified": true,
										"children": {
											"texture": "noxlime",
											"render_method": "blend"
										}
									}
								]
							},
							{
								"key": "minecraft:pick_collision",
								"is_minified": true,
								"children": {
									"origin": [
										-7,
										0,
										-7
									],
									"size": [
										14,
										4,
										14
									]
								}
							},
							{
								"key": "minecraft:entity_collision",
								"is_minified": true,
								"children": {
									"origin": [
										-7,
										0,
										-7
									],
									"size": [
										14,
										4,
										14
									]
								}
							},
							{
								"data": "0",
								"key": "minecraft:block_light_emission"
							},
							{
								"data": "0",
								"key": "minecraft:block_light_absorption"
							}
						]
					},
					{
						"key": "events",
						"is_minified": true,
						"children": {
							"bridge:update_rotation": {
								"set_block_property": {
									"bridge:block_rotation": "query.cardinal_facing_2d"
								}
							}
						}
					}
				]
			},
			{
				"data": "1.16.100",
				"key": "format_version"
			}
		]
	}
}